io4edge_client/__init__.py
io4edge_client/py.typed
io4edge_client/version.py
io4edge_client/analogintypea/__init__.py
io4edge_client/analogintypea/client.py
io4edge_client/analogintypeb/__init__.py
io4edge_client/analogintypeb/client.py
io4edge_client/api/analogInTypeA/python/analogInTypeA/v1alpha1/analogInTypeA_pb2.py
io4edge_client/api/analogInTypeA/python/analogInTypeA/v1alpha1/analogInTypeA_pb2.pyi
io4edge_client/api/analogInTypeB/python/analogInTypeB/v1/analogInTypeB_pb2.py
io4edge_client/api/analogInTypeB/python/analogInTypeB/v1/analogInTypeB_pb2.pyi
io4edge_client/api/binaryIoTypeA/python/binaryIoTypeA/v1alpha1/binaryIoTypeA_pb2.py
io4edge_client/api/binaryIoTypeA/python/binaryIoTypeA/v1alpha1/binaryIoTypeA_pb2.pyi
io4edge_client/api/binaryIoTypeB/python/binaryIoTypeB/v1alpha1/binaryIoTypeB_pb2.py
io4edge_client/api/binaryIoTypeB/python/binaryIoTypeB/v1alpha1/binaryIoTypeB_pb2.pyi
io4edge_client/api/binaryIoTypeC/python/binaryIoTypeC/v1alpha1/binaryIoTypeC_pb2.py
io4edge_client/api/binaryIoTypeC/python/binaryIoTypeC/v1alpha1/binaryIoTypeC_pb2.pyi
io4edge_client/api/binaryIoTypeD/python/binaryIoTypeD/v1/binaryIoTypeD_pb2.py
io4edge_client/api/binaryIoTypeD/python/binaryIoTypeD/v1/binaryIoTypeD_pb2.pyi
io4edge_client/api/bitbusSniffer/python/bitbusSniffer/v1/bitbusSniffer_pb2.py
io4edge_client/api/bitbusSniffer/python/bitbusSniffer/v1/bitbusSniffer_pb2.pyi
io4edge_client/api/canL2/python/canL2/v1alpha1/canL2_pb2.py
io4edge_client/api/canL2/python/canL2/v1alpha1/canL2_pb2.pyi
io4edge_client/api/colorLED/python/colorLED/v1alpha1/colorLED_pb2.py
io4edge_client/api/colorLED/python/colorLED/v1alpha1/colorLED_pb2.pyi
io4edge_client/api/digiwave/python/digiwave/v1/digiwave_pb2.py
io4edge_client/api/digiwave/python/digiwave/v1/digiwave_pb2.pyi
io4edge_client/api/eeprom/python/eeprom/v1alpha1/eeprom_pb2.py
io4edge_client/api/eeprom/python/eeprom/v1alpha1/eeprom_pb2.pyi
io4edge_client/api/google_wellknowntypes/python/google/protobuf/any_pb2.py
io4edge_client-2.4.1.dist-info/METADATA
io4edge_client-2.4.1.dist-info/WHEEL
io4edge_client-2.4.1.dist-info/top_level.txt
io4edge_client-2.4.1.dist-info/RECORD
