Metadata-Version: 2.4
Name: io4edge_client
Version: 2.4.1
Summary: A python library for io4edge devices
Home-page: https://github.com/ci4rail/io4edge-client-python
Author: Ci4Rail GmbH
Author-email: engineering@ci4rail.com
Project-URL: Source Code, https://github.com/ci4rail/io4edge-client-python.git
Classifier: Programming Language :: Python :: 3
Classifier: Operating System :: OS Independent
Requires-Dist: protobuf
Requires-Dist: zeroconf
Dynamic: author
Dynamic: author-email
Dynamic: classifier
Dynamic: description
Dynamic: description-content-type
Dynamic: home-page
Dynamic: project-url
Dynamic: requires-dist
Dynamic: summary
